{
  "main": {
    "id": "78876d58dcae43f2",
    "type": "split",
    "children": [
      {
        "id": "74359c78cce53cb6",
        "type": "tabs",
        "dimension": 67.5550405561993,
        "children": [
          {
            "id": "fdc2790b076420b7",
            "type": "leaf",
            "state": {
              "type": "markdown",
              "state": {
                "file": "LG CNS 면접.md",
                "mode": "source",
                "source": false
              },
              "icon": "lucide-file",
              "title": "LG CNS 면접"
            }
          },
          {
            "id": "4ef47511e7deeb31",
            "type": "leaf",
            "state": {
              "type": "markdown",
              "state": {
                "file": "면접 - 협업.md",
                "mode": "source",
                "source": false
              },
              "icon": "lucide-file",
              "title": "면접 - 협업"
            }
          },
          {
            "id": "a2781494e1cbe5fe",
            "type": "leaf",
            "state": {
              "type": "markdown",
              "state": {
                "file": "기업은행 면접준비.md",
                "mode": "source",
                "source": false
              },
              "icon": "lucide-file",
              "title": "기업은행 면접준비"
            }
          }
        ]
      },
      {
        "id": "51ac177abc9b5e89",
        "type": "tabs",
        "dimension": 32.4449594438007,
        "children": [
          {
            "id": "c9b82356bcd4a800",
            "type": "leaf",
            "state": {
              "type": "outline",
              "state": {
                "file": "LG CNS 면접.md",
                "followCursor": false,
                "showSearch": false,
                "searchQuery": ""
              },
              "icon": "lucide-list",
              "title": "Outline of LG CNS 면접"
            }
          }
        ]
      }
    ],
    "direction": "vertical"
  },
  "left": {
    "id": "7ff942333d048e93",
    "type": "split",
    "children": [
      {
        "id": "fc3e09828d44bd35",
        "type": "tabs",
        "children": [
          {
            "id": "11f1d488c5517a9b",
            "type": "leaf",
            "state": {
              "type": "file-explorer",
              "state": {
                "sortOrder": "alphabetical",
                "autoReveal": false
              },
              "icon": "lucide-folder-closed",
              "title": "Files"
            }
          },
          {
            "id": "970e23febe281321",
            "type": "leaf",
            "state": {
              "type": "search",
              "state": {
                "query": "",
                "matchingCase": false,
                "explainSearch": false,
                "collapseAll": false,
                "extraContext": false,
                "sortOrder": "alphabetical"
              },
              "icon": "lucide-search",
              "title": "검색"
            }
          },
          {
            "id": "1e716a3a09b21e68",
            "type": "leaf",
            "state": {
              "type": "bookmarks",
              "state": {},
              "icon": "lucide-bookmark",
              "title": "Bookmarks"
            }
          }
        ]
      }
    ],
    "direction": "horizontal",
    "width": 200
  },
  "right": {
    "id": "14357fc326fa2d45",
    "type": "split",
    "children": [
      {
        "id": "2b462486db2630f8",
        "type": "tabs",
        "children": [
          {
            "id": "a7f3109a3f00a454",
            "type": "leaf",
            "state": {
              "type": "backlink",
              "state": {
                "file": "LG CNS 2차 면접.md",
                "collapseAll": false,
                "extraContext": false,
                "sortOrder": "alphabetical",
                "showSearch": false,
                "searchQuery": "",
                "backlinkCollapsed": false,
                "unlinkedCollapsed": true
              },
              "icon": "links-coming-in",
              "title": "Backlinks for LG CNS 2차 면접"
            }
          },
          {
            "id": "8eaf7eb50b70542e",
            "type": "leaf",
            "state": {
              "type": "outgoing-link",
              "state": {
                "file": "LG CNS 2차 면접.md",
                "linksCollapsed": false,
                "unlinkedCollapsed": true
              },
              "icon": "links-going-out",
              "title": "Outgoing links from LG CNS 2차 면접"
            }
          },
          {
            "id": "0e6e384624da1a58",
            "type": "leaf",
            "state": {
              "type": "tag",
              "state": {
                "sortOrder": "frequency",
                "useHierarchy": true
              },
              "icon": "lucide-tags",
              "title": "Tags"
            }
          },
          {
            "id": "c31ffe9a990dfcee",
            "type": "leaf",
            "state": {
              "type": "outline",
              "state": {
                "file": "Area/algorithm/동적계획 - 와일드카드.md"
              },
              "icon": "lucide-list",
              "title": "동적계획 - 와일드카드 개요"
            }
          }
        ],
        "currentTab": 1
      }
    ],
    "direction": "horizontal",
    "width": 200,
    "collapsed": true
  },
  "left-ribbon": {
    "hiddenItems": {
      "bases:Create new base": false,
      "switcher:Open quick switcher": false,
      "graph:Open graph view": false,
      "canvas:Create new canvas": false,
      "daily-notes:Open today's daily note": false,
      "templates:Insert template": false,
      "command-palette:Open command palette": false,
      "markdown-importer:Open format converter": false,
      "obsidian-git:Open Git source control": false
    }
  },
  "active": "fdc2790b076420b7",
  "lastOpenFiles": [
    "LG CNS 2차 면접.md",
    "LG CNS 면접.md",
    "기업은행 면접준비.md",
    "면접 - 협업.md",
    "한국투자저축은행 핵심.md",
    "README.md",
    "Plan.md",
    "농협 면접준비.md",
    "면접준비/1자클린아키텍처.md",
    "한국투자 저축은행.md",
    "면접 - 포트폴리오.md",
    "면접 - 과제.md",
    "면접준비/6협업에 관한 질문.md",
    "면접준비/7기술스택.md",
    "면접준비/5주식 시뮬레이션.md",
    "면접준비/AWS CICD.md",
    "면접준비/DBSCAN.md",
    "면접준비/4서울도서이음.md",
    "면접준비/3About 기술 스택.md",
    "Untitled 1.base",
    "Untitled.base",
    "Project/capstone/MSA Kubernetes 배포자동화.md",
    "Project/capstone",
    "Untitled 6.base",
    "Untitled 5.base",
    "Untitled 4.base",
    "Untitled 3.base",
    "면접준비/Typescript.md",
    "면접준비/Redis pubsub.md",
    "면접준비/ELK.md",
    "면접준비/2당근.md",
    "면접준비/1자기소개.md",
    "Untitled 2.base",
    "zz네면/자료구조.md",
    "images/Pasted image 20250723102932.png",
    "images/Pasted image 20250714134954.png",
    "images/Pasted image 20250714114029.png",
    "images/Pasted image 20250627113727.png",
    "images/Pasted image 20250625160011.png",
    "Area/codit",
    "Pasted image 20250723102932.png",
    "Pasted image 20250714134954.png",
    "Pasted image 20250714114029.png",
    "Pasted image 20250627113727.png",
    "Pasted image 20250625160011.png",
    "zz네면"
  ]
}